{
  "name": "Test Level",
  "modelid": "testworld1",
  "levelid": "levelone",
  "assets": {
    "levelModelIds": ["1-pf-2", "1-pf-4", "1-pf-6", "1-pf-10", "1-pil-30"],
    "modelIds": ["dashpowerup", "jumppad1", "door1", "door2"],
    "spriteIds": ["gravityswitch", "pointorb"]
  },
  "environment": {
    "skybox": {
      "folder": "/skybox/greysky/",
      "textures": [
        "/skybox/greysky/1.png",
        "/skybox/greysky/1.png",
        "/skybox/greysky/2.png",
        "/skybox/greysky/1.png",
        "/skybox/greysky/1.png",
        "/skybox/greysky/1.png"
      ]
    }
  },
  "resetPlanes": [
    {
      "position": {
        "x": 0,
        "y": -1,
        "z": 70
      },
      "rotation": {
        "x": 0,
        "y": 0,
        "z": 0
      },
      "width": "5",
      "length": "2000"
    }
  ],
  "levelModels": [
    {
      "modelId": "1-pf-10",
      "position": {
        "x": 0,
        "y": 0,
        "z": 5
      },
      "rotation": {
        "x": -90,
        "y": 0,
        "z": 0
      }
    },
    {
      "modelId": "1-pf-10",
      "position": {
        "x": 0,
        "y": 0,
        "z": 15
      },
      "rotation": {
        "x": -90,
        "y": 0,
        "z": 0
      }
    },
    {
      "modelId": "1-pil-30",
      "position": {
        "x": -1,
        "y": 0,
        "z": 5
      },
      "rotation": {
        "x": -90,
        "y": 0,
        "z": 0
      }
    },
    {
      "modelId": "1-pil-30",
      "position": {
        "x": 2,
        "y": 0,
        "z": 5
      },
      "rotation": {
        "x": -90,
        "y": 0,
        "z": 0
      }
    },
    {
      "modelId": "1-pil-30",
      "position": {
        "x": 2,
        "y": 0,
        "z": 14
      },
      "rotation": {
        "x": -90,
        "y": 0,
        "z": 0
      }
    },
    {
      "modelId": "1-pil-30",
      "position": {
        "x": -1,
        "y": 0,
        "z": 14
      },
      "rotation": {
        "x": -90,
        "y": 0,
        "z": 0
      }
    },
    {
      "modelId": "1-pil-30",
      "position": {
        "x": -1,
        "y": 0,
        "z": 24
      },
      "rotation": {
        "x": -90,
        "y": 0,
        "z": 0
      }
    },
    {
      "modelId": "1-pil-30",
      "position": {
        "x": 2,
        "y": 0,
        "z": 24
      },
      "rotation": {
        "x": -90,
        "y": 0,
        "z": 0
      }
    },
    {
      "modelId": "1-pf-10",
      "position": {
        "x": 0,
        "y": 0,
        "z": 25
      },
      "rotation": {
        "x": -90,
        "y": 0,
        "z": 0
      }
    },
    {
      "modelId": "1-pf-10",
      "position": {
        "x": 0,
        "y": 0,
        "z": 35
      },
      "rotation": {
        "x": -90,
        "y": 0,
        "z": 0
      }
    },
    {
      "modelId": "1-pil-30",
      "position": {
        "x": 2,
        "y": 0,
        "z": 34
      },
      "rotation": {
        "x": -90,
        "y": 0,
        "z": 0
      }
    },
    {
      "modelId": "1-pil-30",
      "position": {
        "x": -1,
        "y": 0,
        "z": 34
      },
      "rotation": {
        "x": -90,
        "y": 0,
        "z": 0
      }
    },
    {
      "modelId": "1-pil-30",
      "position": {
        "x": 2,
        "y": 0,
        "z": 44
      },
      "rotation": {
        "x": -90,
        "y": 0,
        "z": 0
      }
    },
    {
      "modelId": "1-pf-10",
      "position": {
        "x": 0,
        "y": 0,
        "z": 45
      },
      "rotation": {
        "x": -90,
        "y": 0,
        "z": 0
      }
    },
    {
      "modelId": "1-pil-30",
      "position": {
        "x": -1,
        "y": 0,
        "z": 44
      },
      "rotation": {
        "x": -90,
        "y": 0,
        "z": 0
      }
    },
    {
      "modelId": "1-pil-30",
      "position": {
        "x": -1,
        "y": 0,
        "z": 54
      },
      "rotation": {
        "x": -90,
        "y": 0,
        "z": 0
      }
    },
    {
      "modelId": "1-pil-30",
      "position": {
        "x": 2,
        "y": 0,
        "z": 54
      },
      "rotation": {
        "x": -90,
        "y": 0,
        "z": 0
      }
    },
    {
      "modelId": "1-pf-10",
      "position": {
        "x": 0,
        "y": 0,
        "z": 55
      },
      "rotation": {
        "x": -90,
        "y": 0,
        "z": 0
      }
    },
    {
      "modelId": "1-pil-30",
      "position": {
        "x": 2,
        "y": 0,
        "z": 64
      },
      "rotation": {
        "x": -90,
        "y": 0,
        "z": 0
      }
    },
    {
      "modelId": "1-pil-30",
      "position": {
        "x": -1,
        "y": 0,
        "z": 64
      },
      "rotation": {
        "x": -90,
        "y": 0,
        "z": 0
      }
    },
    {
      "modelId": "1-pf-10",
      "position": {
        "x": 0,
        "y": 0,
        "z": 65
      },
      "rotation": {
        "x": -90,
        "y": 0,
        "z": 0
      }
    },
    {
      "modelId": "1-pil-30",
      "position": {
        "x": -1,
        "y": 0,
        "z": 74
      },
      "rotation": {
        "x": -90,
        "y": 0,
        "z": 0
      }
    },
    {
      "modelId": "1-pil-30",
      "position": {
        "x": 2,
        "y": 0,
        "z": 74
      },
      "rotation": {
        "x": -90,
        "y": 0,
        "z": 0
      }
    },
    {
      "modelId": "1-pf-10",
      "position": {
        "x": 0,
        "y": 0,
        "z": 75
      },
      "rotation": {
        "x": -90,
        "y": 0,
        "z": 0
      }
    },
    {
      "modelId": "1-pil-30",
      "position": {
        "x": 2,
        "y": 0,
        "z": 84
      },
      "rotation": {
        "x": -90,
        "y": 0,
        "z": 0
      }
    },
    {
      "modelId": "1-pil-30",
      "position": {
        "x": -1,
        "y": 0,
        "z": 84
      },
      "rotation": {
        "x": -90,
        "y": 0,
        "z": 0
      }
    },
    {
      "modelId": "1-pf-6",
      "position": {
        "x": 0,
        "y": 0,
        "z": 93
      },
      "rotation": {
        "x": -90,
        "y": 0,
        "z": 0
      }
    },
    {
      "modelId": "1-pil-30",
      "position": {
        "x": -1,
        "y": 0,
        "z": 93
      },
      "rotation": {
        "x": -90,
        "y": 0,
        "z": 0
      }
    },
    {
      "modelId": "1-pil-30",
      "position": {
        "x": 2,
        "y": 0,
        "z": 93
      },
      "rotation": {
        "x": -90,
        "y": 0,
        "z": 0
      }
    },
    {
      "modelId": "1-pil-30",
      "position": {
        "x": 2,
        "y": 0,
        "z": 98
      },
      "rotation": {
        "x": -90,
        "y": 0,
        "z": 0
      }
    },
    {
      "modelId": "1-pil-30",
      "position": {
        "x": -1,
        "y": 0,
        "z": 98
      },
      "rotation": {
        "x": -90,
        "y": 0,
        "z": 0
      }
    },
    {
      "modelId": "1-pf-6",
      "position": {
        "x": 0,
        "y": 2,
        "z": 107
      },
      "rotation": {
        "x": -90,
        "y": 0,
        "z": 0
      }
    },
    {
      "modelId": "1-pil-30",
      "position": {
        "x": -1,
        "y": 2,
        "z": 107
      },
      "rotation": {
        "x": -90,
        "y": 0,
        "z": 0
      }
    },
    {
      "modelId": "1-pil-30",
      "position": {
        "x": 2,
        "y": 2,
        "z": 107
      },
      "rotation": {
        "x": -90,
        "y": 0,
        "z": 0
      }
    },
    {
      "modelId": "1-pil-30",
      "position": {
        "x": 2,
        "y": 2,
        "z": 112
      },
      "rotation": {
        "x": -90,
        "y": 0,
        "z": 0
      }
    },
    {
      "modelId": "1-pil-30",
      "position": {
        "x": -1,
        "y": 2,
        "z": 112
      },
      "rotation": {
        "x": -90,
        "y": 0,
        "z": 0
      }
    },
    {
      "modelId": "1-pf-6",
      "position": {
        "x": 0,
        "y": 4,
        "z": 121
      },
      "rotation": {
        "x": -90,
        "y": 0,
        "z": 0
      }
    },
    {
      "modelId": "1-pil-30",
      "position": {
        "x": -1,
        "y": 4,
        "z": 121
      },
      "rotation": {
        "x": -90,
        "y": 0,
        "z": 0
      }
    },
    {
      "modelId": "1-pil-30",
      "position": {
        "x": 2,
        "y": 4,
        "z": 121
      },
      "rotation": {
        "x": -90,
        "y": 0,
        "z": 0
      }
    },
    {
      "modelId": "1-pil-30",
      "position": {
        "x": 2,
        "y": 4,
        "z": 126
      },
      "rotation": {
        "x": -90,
        "y": 0,
        "z": 0
      }
    },
    {
      "modelId": "1-pil-30",
      "position": {
        "x": -1,
        "y": 4,
        "z": 126
      },
      "rotation": {
        "x": -90,
        "y": 0,
        "z": 0
      }
    },
    {
      "modelId": "1-pf-6",
      "position": {
        "x": 0,
        "y": 6,
        "z": 135
      },
      "rotation": {
        "x": -90,
        "y": 0,
        "z": 0
      }
    },
    {
      "modelId": "1-pil-30",
      "position": {
        "x": -1,
        "y": 6,
        "z": 135
      },
      "rotation": {
        "x": -90,
        "y": 0,
        "z": 0
      }
    },
    {
      "modelId": "1-pil-30",
      "position": {
        "x": 2,
        "y": 6,
        "z": 135
      },
      "rotation": {
        "x": -90,
        "y": 0,
        "z": 0
      }
    },
    {
      "modelId": "1-pil-30",
      "position": {
        "x": 2,
        "y": 6,
        "z": 140
      },
      "rotation": {
        "x": -90,
        "y": 0,
        "z": 0
      }
    },
    {
      "modelId": "1-pil-30",
      "position": {
        "x": -1,
        "y": 6,
        "z": 140
      },
      "rotation": {
        "x": -90,
        "y": 0,
        "z": 0
      }
    },
    {
      "modelId": "1-pf-6",
      "position": {
        "x": 0,
        "y": 8,
        "z": 149
      },
      "rotation": {
        "x": -90,
        "y": 0,
        "z": 0
      }
    },
    {
      "modelId": "1-pil-30",
      "position": {
        "x": -1,
        "y": 8,
        "z": 149
      },
      "rotation": {
        "x": -90,
        "y": 0,
        "z": 0
      }
    },
    {
      "modelId": "1-pil-30",
      "position": {
        "x": 2,
        "y": 8,
        "z": 149
      },
      "rotation": {
        "x": -90,
        "y": 0,
        "z": 0
      }
    },
    {
      "modelId": "1-pil-30",
      "position": {
        "x": 2,
        "y": 8,
        "z": 154
      },
      "rotation": {
        "x": -90,
        "y": 0,
        "z": 0
      }
    },
    {
      "modelId": "1-pil-30",
      "position": {
        "x": -1,
        "y": 8,
        "z": 154
      },
      "rotation": {
        "x": -90,
        "y": 0,
        "z": 0
      }
    },
    {
      "modelId": "1-pf-6",
      "position": {
        "x": 0,
        "y": 10,
        "z": 163
      },
      "rotation": {
        "x": -90,
        "y": 0,
        "z": 0
      }
    },
    {
      "modelId": "1-pil-30",
      "position": {
        "x": -1,
        "y": 10,
        "z": 163
      },
      "rotation": {
        "x": -90,
        "y": 0,
        "z": 0
      }
    },
    {
      "modelId": "1-pil-30",
      "position": {
        "x": 2,
        "y": 10,
        "z": 163
      },
      "rotation": {
        "x": -90,
        "y": 0,
        "z": 0
      }
    },
    {
      "modelId": "1-pil-30",
      "position": {
        "x": 2,
        "y": 10,
        "z": 168
      },
      "rotation": {
        "x": -90,
        "y": 0,
        "z": 0
      }
    },
    {
      "modelId": "1-pil-30",
      "position": {
        "x": -1,
        "y": 10,
        "z": 168
      },
      "rotation": {
        "x": -90,
        "y": 0,
        "z": 0
      }
    },
    {
      "modelId": "1-pf-6",
      "position": {
        "x": 0,
        "y": 12,
        "z": 177
      },
      "rotation": {
        "x": -90,
        "y": 0,
        "z": 0
      }
    },
    {
      "modelId": "1-pil-30",
      "position": {
        "x": -1,
        "y": 12,
        "z": 177
      },
      "rotation": {
        "x": -90,
        "y": 0,
        "z": 0
      }
    },
    {
      "modelId": "1-pil-30",
      "position": {
        "x": 2,
        "y": 12,
        "z": 177
      },
      "rotation": {
        "x": -90,
        "y": 0,
        "z": 0
      }
    },
    {
      "modelId": "1-pil-30",
      "position": {
        "x": 2,
        "y": 12,
        "z": 182
      },
      "rotation": {
        "x": -90,
        "y": 0,
        "z": 0
      }
    },
    {
      "modelId": "1-pil-30",
      "position": {
        "x": -1,
        "y": 12,
        "z": 182
      },
      "rotation": {
        "x": -90,
        "y": 0,
        "z": 0
      }
    },
    {
      "modelId": "1-pf-10",
      "position": {
        "x": 0,
        "y": 0,
        "z": 195
      },
      "rotation": {
        "x": -90,
        "y": -6.3611093629270335e-15,
        "z": 0
      }
    },
    {
      "modelId": "1-pil-30",
      "position": {
        "x": -1,
        "y": 0,
        "z": 195
      },
      "rotation": {
        "x": -90,
        "y": 0,
        "z": 0
      }
    },
    {
      "modelId": "1-pil-30",
      "position": {
        "x": 2,
        "y": 0,
        "z": 195
      },
      "rotation": {
        "x": -90,
        "y": 0,
        "z": 0
      }
    },
    {
      "modelId": "1-pil-30",
      "position": {
        "x": 2,
        "y": 0,
        "z": 204
      },
      "rotation": {
        "x": -90,
        "y": 0,
        "z": 0
      }
    },
    {
      "modelId": "1-pil-30",
      "position": {
        "x": -1,
        "y": 0,
        "z": 204
      },
      "rotation": {
        "x": -90,
        "y": 0,
        "z": 0
      }
    },
    {
      "modelId": "1-pf-10",
      "position": {
        "x": 0,
        "y": 0,
        "z": 205
      },
      "rotation": {
        "x": -90,
        "y": -6.3611093629270335e-15,
        "z": 0
      }
    },
    {
      "modelId": "1-pil-30",
      "position": {
        "x": -1,
        "y": 0,
        "z": 214
      },
      "rotation": {
        "x": -90,
        "y": 0,
        "z": 0
      }
    },
    {
      "modelId": "1-pil-30",
      "position": {
        "x": 2,
        "y": 0,
        "z": 214
      },
      "rotation": {
        "x": -90,
        "y": 0,
        "z": 0
      }
    },
    {
      "modelId": "1-pf-10",
      "position": {
        "x": 0,
        "y": 0,
        "z": 215
      },
      "rotation": {
        "x": -90,
        "y": -6.3611093629270335e-15,
        "z": 0
      }
    },
    {
      "modelId": "1-pf-10",
      "position": {
        "x": 0,
        "y": 0,
        "z": 225
      },
      "rotation": {
        "x": -90,
        "y": -6.3611093629270335e-15,
        "z": 0
      }
    },
    {
      "modelId": "1-pil-30",
      "position": {
        "x": 2,
        "y": 0,
        "z": 224
      },
      "rotation": {
        "x": -90,
        "y": 0,
        "z": 0
      }
    },
    {
      "modelId": "1-pil-30",
      "position": {
        "x": -1,
        "y": 0,
        "z": 224
      },
      "rotation": {
        "x": -90,
        "y": 0,
        "z": 0
      }
    },
    {
      "modelId": "1-pil-30",
      "position": {
        "x": -1,
        "y": 0,
        "z": 234
      },
      "rotation": {
        "x": -90,
        "y": 0,
        "z": 0
      }
    },
    {
      "modelId": "1-pil-30",
      "position": {
        "x": 2,
        "y": 0,
        "z": 234
      },
      "rotation": {
        "x": -90,
        "y": 0,
        "z": 0
      }
    },
    {
      "modelId": "1-pf-6",
      "position": {
        "x": 0,
        "y": 5,
        "z": 240
      },
      "rotation": {
        "x": -90,
        "y": 0,
        "z": 0
      }
    },
    {
      "modelId": "1-pil-30",
      "position": {
        "x": 2,
        "y": 5,
        "z": 240
      },
      "rotation": {
        "x": -90,
        "y": 0,
        "z": 0
      }
    },
    {
      "modelId": "1-pil-30",
      "position": {
        "x": -1,
        "y": 5,
        "z": 240
      },
      "rotation": {
        "x": -90,
        "y": 0,
        "z": 0
      }
    },
    {
      "modelId": "1-pil-30",
      "position": {
        "x": -1,
        "y": 5,
        "z": 245
      },
      "rotation": {
        "x": -90,
        "y": 0,
        "z": 0
      }
    },
    {
      "modelId": "1-pil-30",
      "position": {
        "x": 2,
        "y": 5,
        "z": 245
      },
      "rotation": {
        "x": -90,
        "y": 0,
        "z": 0
      }
    },
    {
      "modelId": "1-pf-6",
      "position": {
        "x": 0,
        "y": 10,
        "z": 252
      },
      "rotation": {
        "x": -90,
        "y": 0,
        "z": 0
      }
    },
    {
      "modelId": "1-pil-30",
      "position": {
        "x": 2,
        "y": 10,
        "z": 252
      },
      "rotation": {
        "x": -90,
        "y": 0,
        "z": 0
      }
    },
    {
      "modelId": "1-pil-30",
      "position": {
        "x": -1,
        "y": 10,
        "z": 252
      },
      "rotation": {
        "x": -90,
        "y": 0,
        "z": 0
      }
    },
    {
      "modelId": "1-pil-30",
      "position": {
        "x": -1,
        "y": 10,
        "z": 257
      },
      "rotation": {
        "x": -90,
        "y": 0,
        "z": 0
      }
    },
    {
      "modelId": "1-pil-30",
      "position": {
        "x": 2,
        "y": 10,
        "z": 257
      },
      "rotation": {
        "x": -90,
        "y": 0,
        "z": 0
      }
    },
    {
      "modelId": "1-pf-6",
      "position": {
        "x": 0,
        "y": 15,
        "z": 264
      },
      "rotation": {
        "x": -90,
        "y": 0,
        "z": 0
      }
    },
    {
      "modelId": "1-pil-30",
      "position": {
        "x": 2,
        "y": 15,
        "z": 264
      },
      "rotation": {
        "x": -90,
        "y": 0,
        "z": 0
      }
    },
    {
      "modelId": "1-pil-30",
      "position": {
        "x": -1,
        "y": 15,
        "z": 264
      },
      "rotation": {
        "x": -90,
        "y": 0,
        "z": 0
      }
    },
    {
      "modelId": "1-pil-30",
      "position": {
        "x": -1,
        "y": 15,
        "z": 269
      },
      "rotation": {
        "x": -90,
        "y": 0,
        "z": 0
      }
    },
    {
      "modelId": "1-pil-30",
      "position": {
        "x": 2,
        "y": 15,
        "z": 269
      },
      "rotation": {
        "x": -90,
        "y": 0,
        "z": 0
      }
    },
    {
      "modelId": "1-pf-6",
      "position": {
        "x": 0,
        "y": 20,
        "z": 276
      },
      "rotation": {
        "x": -90,
        "y": 0,
        "z": 0
      }
    },
    {
      "modelId": "1-pil-30",
      "position": {
        "x": 2,
        "y": 20,
        "z": 276
      },
      "rotation": {
        "x": -90,
        "y": 0,
        "z": 0
      }
    },
    {
      "modelId": "1-pil-30",
      "position": {
        "x": -1,
        "y": 20,
        "z": 276
      },
      "rotation": {
        "x": -90,
        "y": 0,
        "z": 0
      }
    },
    {
      "modelId": "1-pil-30",
      "position": {
        "x": -1,
        "y": 20,
        "z": 281
      },
      "rotation": {
        "x": -90,
        "y": 0,
        "z": 0
      }
    },
    {
      "modelId": "1-pil-30",
      "position": {
        "x": 2,
        "y": 20,
        "z": 281
      },
      "rotation": {
        "x": -90,
        "y": 0,
        "z": 0
      }
    },
    {
      "modelId": "1-pf-4",
      "position": {
        "x": 0,
        "y": 20,
        "z": 287
      },
      "rotation": {
        "x": -90,
        "y": 0,
        "z": 0
      }
    },
    {
      "modelId": "1-pf-4",
      "position": {
        "x": 0,
        "y": 20,
        "z": 296
      },
      "rotation": {
        "x": -90,
        "y": 0,
        "z": 0
      }
    },
    {
      "modelId": "1-pf-4",
      "position": {
        "x": 0,
        "y": 20,
        "z": 305
      },
      "rotation": {
        "x": -90,
        "y": 0,
        "z": 0
      }
    },
    {
      "modelId": "1-pf-4",
      "position": {
        "x": 0,
        "y": 14,
        "z": 321
      },
      "rotation": {
        "x": -90,
        "y": 0,
        "z": 0
      }
    },
    {
      "modelId": "1-pil-30",
      "position": {
        "x": 2,
        "y": 20,
        "z": 287
      },
      "rotation": {
        "x": -90,
        "y": 0,
        "z": 0
      }
    },
    {
      "modelId": "1-pil-30",
      "position": {
        "x": -1,
        "y": 20,
        "z": 287
      },
      "rotation": {
        "x": -90,
        "y": 0,
        "z": 0
      }
    },
    {
      "modelId": "1-pil-30",
      "position": {
        "x": -1,
        "y": 20,
        "z": 290
      },
      "rotation": {
        "x": -90,
        "y": 0,
        "z": 0
      }
    },
    {
      "modelId": "1-pil-30",
      "position": {
        "x": 2,
        "y": 20,
        "z": 290
      },
      "rotation": {
        "x": -90,
        "y": 0,
        "z": 0
      }
    },
    {
      "modelId": "1-pil-30",
      "position": {
        "x": 2,
        "y": 20,
        "z": 296
      },
      "rotation": {
        "x": -90,
        "y": 0,
        "z": 0
      }
    },
    {
      "modelId": "1-pil-30",
      "position": {
        "x": -1,
        "y": 20,
        "z": 296
      },
      "rotation": {
        "x": -90,
        "y": 0,
        "z": 0
      }
    },
    {
      "modelId": "1-pil-30",
      "position": {
        "x": -1,
        "y": 20,
        "z": 299
      },
      "rotation": {
        "x": -90,
        "y": 0,
        "z": 0
      }
    },
    {
      "modelId": "1-pil-30",
      "position": {
        "x": 2,
        "y": 20,
        "z": 299
      },
      "rotation": {
        "x": -90,
        "y": 0,
        "z": 0
      }
    },
    {
      "modelId": "1-pil-30",
      "position": {
        "x": 2,
        "y": 20,
        "z": 305
      },
      "rotation": {
        "x": -90,
        "y": 0,
        "z": 0
      }
    },
    {
      "modelId": "1-pil-30",
      "position": {
        "x": -1,
        "y": 20,
        "z": 305
      },
      "rotation": {
        "x": -90,
        "y": 0,
        "z": 0
      }
    },
    {
      "modelId": "1-pil-30",
      "position": {
        "x": -1,
        "y": 20,
        "z": 308
      },
      "rotation": {
        "x": -90,
        "y": 0,
        "z": 0
      }
    },
    {
      "modelId": "1-pil-30",
      "position": {
        "x": 2,
        "y": 20,
        "z": 308
      },
      "rotation": {
        "x": -90,
        "y": 0,
        "z": 0
      }
    },
    {
      "modelId": "1-pil-30",
      "position": {
        "x": 2,
        "y": 20,
        "z": 308
      },
      "rotation": {
        "x": -90,
        "y": 0,
        "z": 0
      }
    },
    {
      "modelId": "1-pil-30",
      "position": {
        "x": 2,
        "y": 14,
        "z": 321
      },
      "rotation": {
        "x": -90,
        "y": 0,
        "z": 0
      }
    },
    {
      "modelId": "1-pil-30",
      "position": {
        "x": -1,
        "y": 14,
        "z": 321
      },
      "rotation": {
        "x": -90,
        "y": 0,
        "z": 0
      }
    },
    {
      "modelId": "1-pil-30",
      "position": {
        "x": -1,
        "y": 14,
        "z": 324
      },
      "rotation": {
        "x": -90,
        "y": 0,
        "z": 0
      }
    },
    {
      "modelId": "1-pil-30",
      "position": {
        "x": 2,
        "y": 14,
        "z": 324
      },
      "rotation": {
        "x": -90,
        "y": 0,
        "z": 0
      }
    },
    {
      "modelId": "1-pf-4",
      "position": {
        "x": 0,
        "y": 7,
        "z": 337
      },
      "rotation": {
        "x": -90,
        "y": 0,
        "z": 0
      }
    },
    {
      "modelId": "1-pil-30",
      "position": {
        "x": 2,
        "y": 7,
        "z": 337
      },
      "rotation": {
        "x": -90,
        "y": 0,
        "z": 0
      }
    },
    {
      "modelId": "1-pil-30",
      "position": {
        "x": -1,
        "y": 7,
        "z": 337
      },
      "rotation": {
        "x": -90,
        "y": 0,
        "z": 0
      }
    },
    {
      "modelId": "1-pil-30",
      "position": {
        "x": -1,
        "y": 7,
        "z": 340
      },
      "rotation": {
        "x": -90,
        "y": 0,
        "z": 0
      }
    },
    {
      "modelId": "1-pil-30",
      "position": {
        "x": 2,
        "y": 7,
        "z": 340
      },
      "rotation": {
        "x": -90,
        "y": 0,
        "z": 0
      }
    },
    {
      "modelId": "1-pf-4",
      "position": {
        "x": 0,
        "y": 0,
        "z": 353
      },
      "rotation": {
        "x": -90,
        "y": 0,
        "z": 0
      }
    },
    {
      "modelId": "1-pil-30",
      "position": {
        "x": 2,
        "y": 0,
        "z": 353
      },
      "rotation": {
        "x": -90,
        "y": 0,
        "z": 0
      }
    },
    {
      "modelId": "1-pil-30",
      "position": {
        "x": -1,
        "y": 0,
        "z": 353
      },
      "rotation": {
        "x": -90,
        "y": 0,
        "z": 0
      }
    },
    {
      "modelId": "1-pil-30",
      "position": {
        "x": -1,
        "y": 0,
        "z": 356
      },
      "rotation": {
        "x": -90,
        "y": 0,
        "z": 0
      }
    },
    {
      "modelId": "1-pil-30",
      "position": {
        "x": 2,
        "y": 0,
        "z": 356
      },
      "rotation": {
        "x": -90,
        "y": 0,
        "z": 0
      }
    },
    {
      "modelId": "1-pf-10",
      "position": {
        "x": 0,
        "y": 0,
        "z": 367
      },
      "rotation": {
        "x": -90,
        "y": 0,
        "z": 0
      }
    },
    {
      "modelId": "1-pil-30",
      "position": {
        "x": 2,
        "y": 0,
        "z": 367
      },
      "rotation": {
        "x": -90,
        "y": 0,
        "z": 0
      }
    },
    {
      "modelId": "1-pil-30",
      "position": {
        "x": -1,
        "y": 0,
        "z": 367
      },
      "rotation": {
        "x": -90,
        "y": 0,
        "z": 0
      }
    },
    {
      "modelId": "1-pil-30",
      "position": {
        "x": -1,
        "y": 0,
        "z": 376
      },
      "rotation": {
        "x": -90,
        "y": 0,
        "z": 0
      }
    },
    {
      "modelId": "1-pil-30",
      "position": {
        "x": 2,
        "y": 0,
        "z": 376
      },
      "rotation": {
        "x": -90,
        "y": 0,
        "z": 0
      }
    },
    {
      "modelId": "1-pf-10",
      "position": {
        "x": 0,
        "y": 0,
        "z": 377
      },
      "rotation": {
        "x": -90,
        "y": 0,
        "z": 0
      }
    },
    {
      "modelId": "1-pil-30",
      "position": {
        "x": 2,
        "y": 0,
        "z": 386
      },
      "rotation": {
        "x": -90,
        "y": 0,
        "z": 0
      }
    },
    {
      "modelId": "1-pil-30",
      "position": {
        "x": -1,
        "y": 0,
        "z": 386
      },
      "rotation": {
        "x": -90,
        "y": 0,
        "z": 0
      }
    },
    {
      "modelId": "1-pf-10",
      "position": {
        "x": 0,
        "y": 0,
        "z": 387
      },
      "rotation": {
        "x": -90,
        "y": 0,
        "z": 0
      }
    },
    {
      "modelId": "1-pil-30",
      "position": {
        "x": -1,
        "y": 0,
        "z": 396
      },
      "rotation": {
        "x": -90,
        "y": 0,
        "z": 0
      }
    },
    {
      "modelId": "1-pil-30",
      "position": {
        "x": 2,
        "y": 0,
        "z": 396
      },
      "rotation": {
        "x": -90,
        "y": 0,
        "z": 0
      }
    },
    {
      "modelId": "1-pf-10",
      "position": {
        "x": 0,
        "y": 0,
        "z": 5
      },
      "rotation": {
        "x": -90,
        "y": 0,
        "z": 0
      }
    }
  ],
  "objects": [
    {
      "className": "Door",
      "type": "door",
      "position": {
        "x": -1,
        "y": 3,
        "z": 40
      },
      "rotation": {
        "x": 90,
        "y": 0,
        "z": 0
      },
      "side": "right",
      "distance": 5,
      "modelid": "door1"
    },

    {
      "className": "Door",
      "type": "door",
      "position": {
        "x": 1,
        "y": 3,
        "z": 40
      },
      "rotation": {
        "x": 90,
        "y": 0,
        "z": 0
      },
      "side": "left",
      "distance": 5,
      "modelid": "door2"
    },
    {
      "className": "ActionNode",
      "type": "actionNode",
      "position": {
        "x": 0,
        "y": 1,
        "z": 20
      },
      "rotation": {
        "x": 0,
        "y": 0,
        "z": 0
      },
      "action": "action1",
      "distance": "5"
    },
    {
      "className": "PointOrb",
      "type": "pointorb",
      "position": {
        "x": 0,
        "y": 1,
        "z": 20
      },
      "rotation": {
        "x": 0,
        "y": 0,
        "z": 0
      },
      "spriteid": "pointorb",
      "points": "10"
    },
    {
      "type": "normal",
      "position": {
        "x": 0,
        "y": 0,
        "z": 0
      },
      "rotation": {
        "x": 0,
        "y": 0,
        "z": 0
      },
      "modelid": "checkpoint1",
      "difficulty": "normal"
    }
  ]
}
